oxidized_transformers-0.1.0.dist-info/METADATA
oxidized_transformers-0.1.0.dist-info/WHEEL
oxidized_transformers/__init__.py
oxidized_transformers/oxidized_transformers.abi3.so
oxidized_transformers-0.1.0.dist-info/RECORD
