Metadata-Version: 2.3
Name: oxidized-transformers
Version: 0.1.0
Classifier: Programming Language :: Rust
Classifier: Programming Language :: Python :: Implementation :: CPython
Summary: Transformers library (not functional yet)
Home-Page: https://github.com/danieldk/oxidized-transformers
License: MIT
Requires-Python: >=3.8
Project-URL: Source Code, https://github.com/danieldk/oxidized-transformers
